{"topic_id": "16787", "word_level_id": "14", "tag_id": "0", "word": "heckle", "word_audio": "heckle.mp3", "image_file": "heckle_16787_20231106_001d62c8.jpg", "accent": "/ˈhekl/", "mean_cn": "v.诘问，起哄", "mean_en": "\"to interrupt (someone", "sentence_phrase": "", "deformation_img": "20140722_18_54_55_610_v3.png", "sentence": "The audience heckled the band\\u0027s awful performance.", "sentence_trans": "观众们对着乐队的糟糕表演起哄。", "sentence_audio": "3_0_20160720072336_98151_c.aac", "cloze_data": "{\"syllable\":\"heck-le\"", "cloze": "he[ck]-le", "options": "[\"que|kn|ng|nk\"]", "tips": "[[\"he[ck]\"", "word_etyma": ""}