{"topic_id": "15285", "word_level_id": "12", "tag_id": "0", "word": "bereft", "word_audio": "bereft.mp3", "image_file": "i_12_15285_0_2_20150808183140.jpg", "accent": "/bɪˈreft/", "mean_cn": "adj.失去亲人的", "mean_en": "sad because a family member or friend has died", "sentence_phrase": "", "deformation_img": "", "sentence": "The bereft woman mourns the death of her husband.", "sentence_trans": "这个丧夫的女人对丈夫的离世感到悲痛。", "sentence_audio": "sa_12_15285_0_2_20150808183140.aac", "cloze_data": "{\"syllable\":\"bereft\"", "cloze": "b[ere]ft", "options": "[\"are|ire|ore|ure\"]", "tips": "[[\"unb[ere]ft\"]]}", "word_etyma": ""}