{"topic_id": "11593", "word_level_id": "12", "tag_id": "0", "word": "discretionary", "word_audio": "us_discretionary_20230918114014477_305cb7b2ee222f634a4c.mp3", "image_file": "7fdb3334b954c095b32f76c003c70bf8_121422_1719984004.jpg", "accent": "/dɪˈskrɛʃəˌnɛri/", "mean_cn": "adj.任意的；分立的，自理自由的", "mean_en": "available to be used when and how you decide", "sentence_phrase": "", "deformation_img": "", "sentence": "Judges have great discretionary powers in ruling on cases. ", "sentence_trans": "法官在判决案件时具有极大的自由裁量权。", "sentence_audio": "us_Judges_have_20240703132017416_47f4b376cb6063f06805.mp3", "cloze_data": "{\"syllable\":\"dis-cre-tionary\"", "cloze": "dis-cre-t[ion]ary", "options": "[\"ing|ang|ong|ung\"]", "tips": "[[\"not[ion]ary\"", "word_etyma": "dis不 ＋ cret搞清 ＋ ion表行为 ＋ ary关于…的 → discretionary任意的；自由决定的"}