{"topic_id": "16457", "word_level_id": "1157", "tag_id": "0", "word": "hear", "word_audio": "hear.mp3", "image_file": "6e3355a431c5edb330afbcedbc58668c_55857_1736416851.jpg", "accent": "/hɪr/", "mean_cn": "v.听见", "mean_en": "to listen to (someone or something)", "sentence_phrase": "", "deformation_img": "d_69_12959_0_4_20150809003351.png", "sentence": "What did you say? I can\\u0027t quite hear you.", "sentence_trans": "你说什么？我听不清楚。", "sentence_audio": "rrswjaplxlxg4z88a7r3mmbenrv3jpuh.mp3", "cloze_data": "{\"syllable\":\"hear\"", "cloze": "h[ear]", "options": "[\"eer|ier|eir|air\"]", "tips": "[[\"beh[ear]\"", "word_etyma": ""}