{"topic_id": "440", "word_level_id": "15", "tag_id": "0", "word": "cede", "word_audio": "0620004370208ad9ec2480b946a0e544_17306_1527582200.mp3", "image_file": "4d35308b6f269300e7d1125da6bdcef0_165914_1527582210.jpeg", "accent": "/siːd/", "mean_cn": "v.放弃；割让（领土）", "mean_en": "\"to give control of (something) to another person", "sentence_phrase": "", "deformation_img": "20140829_21_27_13_464_v3.png", "sentence": "He had to cede the power to another general after losing the battle.", "sentence_trans": "输掉这场战役之后，他只得把兵权交给另一位将军。", "sentence_audio": "1f9fdb18a5c7b960156cb93af17542d5_35558_1527582226.mp3", "cloze_data": "{\"syllable\":\"cede\"", "cloze": "c[e]de", "options": "[\"a|i|o|u\"]", "tips": "[[\"rec[e]de\"", "word_etyma": "cede走 → 走开 → 割让 → cede割让，放弃"}