{"topic_id": "11523", "word_level_id": "12", "tag_id": "0", "word": "chordate", "word_audio": "chordate.mp3", "image_file": "i_12_11523_0_2_20150808182026.jpg", "accent": "/\\u0027kɔːˌdeɪt/", "mean_cn": "n.脊索动物；  adj.【动】脊索动物的", "mean_en": "any animal of the phylum Chordata having a notochord or spinal column", "sentence_phrase": "", "deformation_img": "", "sentence": "All birds are classed as chordates because they have backbones.", "sentence_trans": "所有鸟类都被归为脊索动物，因为它们有脊骨。", "sentence_audio": "sa_12_11523_0_2_20150808182026.aac", "cloze_data": "{\"syllable\":\"chor-date\"", "cloze": "ch[or]-date", "options": "[\"ar|er|ir|ur|a\"]", "tips": "[[\"ach[or]\"", "word_etyma": ""}