{"topic_id": "17067", "word_level_id": "14", "tag_id": "0", "word": "cognizant", "word_audio": "cognizant.mp3", "image_file": "818780f3473da2cb0e47a4967c88e27d_84516_1694141398.jpg", "accent": "/ˈkɑːɡnɪzənt/", "mean_cn": "adj.认识到的，意识到的，了解的", "mean_en": "aware of something", "sentence_phrase": "", "deformation_img": "", "sentence": "I don\\u0027t need to read this book: I\\u0027m already cognizant of everything in it.", "sentence_trans": "我不需要看这本书：我已经对里面所有的内容有所认知了。", "sentence_audio": "sa_14_17067_0_2_20150808184412.aac", "cloze_data": "{\"syllable\":\"cog-nizant\"", "cloze": "cog-niz[an]t", "options": "[\"en|in|on|un|e|i|a|o|u\"]", "tips": "[[\"incogniz[an]t\"", "word_etyma": "cogn知道 ＋ iz使... ＋ ant...的 → cognizant知晓的"}