{"topic_id": "16275", "word_level_id": "14", "tag_id": "0", "word": "coltish", "word_audio": "coltish.mp3", "image_file": "9e2e26cbe1301abb841aa0262b8e2856_189455_1699607617.jpg", "accent": "/ˈkoʊltɪʃ/", "mean_cn": "adj.不受拘束的，活泼但笨拙的，似小马的", "mean_en": "given to merry frolicking", "sentence_phrase": "", "deformation_img": "", "sentence": "The child\\u0027s move is coltish. ", "sentence_trans": "这个孩子的行为像小马般活泼。", "sentence_audio": "us_The_childs_20240422140346912_fa7c47481a9a1d6ff9c7.mp3", "cloze_data": "{\"syllable\":\"coltish\"", "cloze": "c[olt]ish", "options": "[\"old|olk|oll|ost\"]", "tips": "[[\"c[olt]ishly\"", "word_etyma": "colt小马驹 ＋ ish表形容词，“像…一样，有的…” → coltish放荡不羁"}