{"topic_id": "2100", "word_level_id": "15", "tag_id": "0", "word": "pore", "word_audio": "us_pore_20231102110710337_0c618bbf6ce2128bd916.mp3", "image_file": "i_2_2100_0_3_20150808141850-gigapixel-scale.jpg", "accent": "/pɔːr/", "mean_cn": "n.毛孔；气孔；孔隙；  v.深思熟虑，仔细阅读，审视", "mean_en": "one of the very small holes in your skin that sweat can pass through; one of the similar small holes in the surface of a plant or a rock", "sentence_phrase": "", "deformation_img": "20140823_00_30_54_591_v3.png", "sentence": "The sweat seeps through pores.", "sentence_trans": "汗水从毛孔中渗透出来。", "sentence_audio": "3_66_20170923150113_61569_c.aac", "cloze_data": "{\"syllable\":\"pore\"", "cloze": "p[ore]", "options": "[\"are|ere|ire|ure\"]", "tips": "[[\"autop[ore]\"", "word_etyma": ""}