{"topic_id": "10160", "word_level_id": "14", "tag_id": "0", "word": "smart", "word_audio": "smart.mp3", "image_file": "d2545a23c2bd708ffa5db597d8f6055d_125699_1701052153.jpg", "accent": "/smɑːrt/", "mean_cn": "v.难过，烦恼；  adj.聪明的，机灵的；时髦的，衣着讲究的", "mean_en": "to feel a sharp stinging pain in a part of your body", "sentence_phrase": "", "deformation_img": "d_24_10160_0_3_20150808230353.png", "sentence": "He is still smarting from defeat last week.", "sentence_trans": "他仍为上星期的惨败而难过。", "sentence_audio": "us_He_is_20231127103232049_9501fc28048e8a0dc0eb.mp3", "cloze_data": "{\"syllable\":\"smart\"", "cloze": "sm[ar]t", "options": "[\"er|ir|or|ur|a\"]", "tips": "[[\"sm[ar]tly\"", "word_etyma": ""}