{"topic_id": "5825", "word_level_id": "1157", "tag_id": "0", "word": "capitalist", "word_audio": "us_capitalist_20231219110539568_6ecb35e7ee3511c28a13.mp3", "image_file": "d3777d7b57bd49f4e9439144c3338f79_101640_1729761026.jpg", "accent": "/ˈkæpɪtəlɪst/", "mean_cn": "n.资本家，资本主义者", "mean_en": "a person who believes that capitalism is the best kind of economic system", "sentence_phrase": "", "deformation_img": "", "sentence": "A capitalist believes that you must spend money to make money.", "sentence_trans": "资本家认为必须通过花钱来赚钱。", "sentence_audio": "sa_9_5825_0_2_20150808151521.aac", "cloze_data": "{\"syllable\":\"ca-pi-tal-ist\"", "cloze": "ca-p[i]-t[al]-ist", "options": "[\"a|e|o|u\"", "tips": "[[\"p[i]\"", "word_etyma": "capital资本 + ist信仰者，专家 → capitalist资本家（的）"}