{"topic_id": "15310", "word_level_id": "12", "tag_id": "0", "word": "Spaniard", "word_audio": "spaniard.mp3", "image_file": "20120811_03_44_22_422.jpg", "accent": "/ˈspænjərd/", "mean_cn": "n.西班牙人", "mean_en": "a native or inhabitant of Spain", "sentence_phrase": "", "deformation_img": "", "sentence": "A Spaniard is someone who comes from Spain.", "sentence_trans": "来自西班牙的人就是西班牙人。", "sentence_audio": "sa_12_15310_0_2_20150808183226.aac", "cloze_data": "{\"syllable\":\"Spaniard\"", "cloze": "Spani[ar]d", "options": "[\"er|ir|or|ur|a\"]", "tips": "[[]]}", "word_etyma": "Spani\\u003dSpain西班牙 ＋ ard表示人 → Spaniard西班牙人"}