{"topic_id": "8691", "word_level_id": "14", "tag_id": "0", "word": "penchant", "word_audio": "penchant.mp3", "image_file": "98a56ce7b041965e8b31ba829d3fe66f_89714_1695894599.jpg", "accent": "/ˈpentʃənt/", "mean_cn": "n.倾向，爱好", "mean_en": "a special liking for something", "sentence_phrase": "", "deformation_img": "", "sentence": "\"She has a penchant for vegetables", "sentence_trans": "比起蛋糕，她更倾向吃蔬菜。", "sentence_audio": "us_She_has_20230928175131406_47f233360b2a93f21fde.mp3", "cloze_data": "{\"syllable\":\"pen-chant\"", "cloze": "p[en]-chant", "options": "[\"in|on|un|an|e|i|a|o|u\"]", "tips": "[[\"asp[en]\"", "word_etyma": ""}