{"topic_id": "2955", "word_level_id": "15", "tag_id": "0", "word": "cataclysm", "word_audio": "cataclysm.mp3", "image_file": "i_15_2955_0_3_20150808154305.jpg", "accent": "/ˈkætəklɪzəm/", "mean_cn": "n.灾难（常指大洪水或地震），剧变", "mean_en": "\"something that causes great destruction", "sentence_phrase": "", "deformation_img": "20140812_17_48_29_903_v3.png", "sentence": "\"The storm was a cataclysm", "sentence_trans": "这场暴风雨是一个灾难，带来了大量的闪电和雨水。", "sentence_audio": "us_The_storm_20241009154812123_cdabaa3045ce3b8d88d7.mp3", "cloze_data": "{\"syllable\":\"ca-ta-clysm\"", "cloze": "ca-t[a]-clysm", "options": "[\"e|i|o|u\"]", "tips": "[[\"t[a]\"", "word_etyma": "cata向下+clys猛冲+m→洪水"}