{"topic_id": "1805", "word_level_id": "15", "tag_id": "0", "word": "maritime", "word_audio": "us_maritime_20231222100132543_05a447f4caae5fb7e486.mp3", "image_file": "1425952555330-gigapixel-scale.jpg", "accent": "/ˈmærɪtaɪm/", "mean_cn": "adj.海事的，海上的，沿海的，近海的", "mean_en": "located near or next to the sea", "sentence_phrase": "A maritime nation", "deformation_img": "d_106_1805_0_2_20150809064242.png", "sentence": "A maritime nation should be aware of tsunami.", "sentence_trans": "沿海的国家应警惕海啸。", "sentence_audio": "sa_4_1805_0_3_20150808144435.aac", "cloze_data": "{\"syllable\":\"Mar-itime\"", "cloze": "M[ar]-itime", "options": "[\"er|ir|or|ur|a\"]", "tips": "[[\"M[ar]\"", "word_etyma": "mari海洋+time\\u003dtim害怕→海的"}