{"topic_id": "8660", "word_level_id": "12", "tag_id": "0", "word": "alligator", "word_audio": "alligator.mp3", "image_file": "9acb5b36a1dd1db544b52360a9ef0fbd_125391_1656405547.jpg", "accent": "/ˈælɪɡeɪtər/", "mean_cn": "n.短吻鳄（一种鳄鱼）", "mean_en": "\"a large reptile that has a long body", "sentence_phrase": "", "deformation_img": "", "sentence": "Two cute alligators are standing together.", "sentence_trans": "两个可爱的短吻鳄正站在一起。", "sentence_audio": "us_Two_cute_20220628164028759_87981fffb6251f497528.mp3", "cloze_data": "{\"syllable\":\"al-li-ga-tor\"", "cloze": "[all]i-ga-tor", "options": "[\"ald|alk|alm|alt|ial\"]", "tips": "[[\"[all]iable\"", "word_etyma": ""}