{"topic_id": "8090", "word_level_id": "12", "tag_id": "0", "word": "total", "word_audio": "total.mp3", "image_file": "f331585c2af9c3587ce8e1633604adc8_150863_1732271005.jpg", "accent": "/ˈtoʊtl/", "mean_cn": "adj.整个的，总体的；  n.总数", "mean_en": "being the amount or number after everyone or everything is counted or added together", "sentence_phrase": "", "deformation_img": "d_24_8090_0_4_20150808225429.png", "sentence": "A total of 340 dollars was spent.", "sentence_trans": "总共花费了340美元。", "sentence_audio": "us_A_total_20241122182300781_df014bfca22dd4299c45.mp3", "cloze_data": "{\"syllable\":\"to-tal\"", "cloze": "to-t[al]", "options": "[\"el|le|nl|ol\"]", "tips": "[[\"t[al]\"", "word_etyma": "tot全部 + al表形容词 → total总体的"}