{"topic_id": "6831", "word_level_id": "12", "tag_id": "0", "word": "reef", "word_audio": "us_reef_20231218135411660_ada073aabfe9dfdfc185.mp3", "image_file": "reef_6831_20231106_2b1b10a3.jpg", "accent": "/riːf/", "mean_cn": "n.礁", "mean_en": "a long line of rocks or sand near the surface of the sea", "sentence_phrase": "", "deformation_img": "", "sentence": "The coral reef in the ocean is a spectacular sight.", "sentence_trans": "大海中的珊瑚礁真是壮观！", "sentence_audio": "chtd5mznuk66szpfxgfm5czle8vdfzaw.mp3", "cloze_data": "{\"syllable\":\"reef\"", "cloze": "r[ee]f", "options": "[\"ea|ie|ii|ye|e\"]", "tips": "[[\"r[ee]fing\"]]}", "word_etyma": ""}