{"topic_id": "2962", "word_level_id": "12", "tag_id": "0", "word": "constrict", "word_audio": "us_constrict_20231220105811687_35ae02f83b2ce8ec4730.mp3", "image_file": "864891a4e956906365acf42ffcbd30e7_155586_1561953075.jpg", "accent": "/kənˈstrɪkt/", "mean_cn": "v.约束，收缩，妨碍", "mean_en": "to become tighter or narrower; to make something tighter or narrower; to limit or restrict what somebody is able to do", "sentence_phrase": "", "deformation_img": "20140731_15_15_55_885_v3.png", "sentence": "This tight corset constricts her body.", "sentence_trans": "这个束腰把她的身体收得很紧。", "sentence_audio": "0b96f868a348d5af5dba5572e713521b_26258_1561953074.mp3", "cloze_data": "{\"syllable\":\"con-strict\"", "cloze": "c[on]-strict", "options": "[\"en|in|un|an|e|i|a|o|u\"]", "tips": "[[\"c[on]\"", "word_etyma": "con一起 + strict拉紧，压 → 拉回来 → constrict限制"}