{"topic_id": "6957", "word_level_id": "15", "tag_id": "0", "word": "economy", "word_audio": "us_economy_20231215132548458_04657a5928b722e22b25.mp3", "image_file": "i_1_6957_0_3_20150808125652-gigapixel-scale.jpg", "accent": "/ɪˈkɑːnəmi/", "mean_cn": "n.经济", "mean_en": "\"the relationship between production", "sentence_phrase": "", "deformation_img": "d_1_6957_0_3_20150808125652.png", "sentence": "The economy is improving and people have more money.", "sentence_trans": "经济正在改善，人们也有了更多的钱。", "sentence_audio": "sa_1_6957_0_3_20150808125652.aac", "cloze_data": "{\"syllable\":\"e-co-no-my\"", "cloze": "e-c[o]-n[o]-my", "options": "[\"a|e|i|u\"", "tips": "[[\"alc[o]\"", "word_etyma": "eco环境，经济 + nomy学术领域 → economy经济（学）"}