{"topic_id": "15462", "word_level_id": "15", "tag_id": "0", "word": "clamber", "word_audio": "clamber.mp3", "image_file": "20120818_04_16_36_373.jpg", "accent": "/ˈklæmbər/", "mean_cn": "v.攀登，爬上", "mean_en": "to climb or crawl in an awkward way", "sentence_phrase": "clambered up", "deformation_img": "20140801_16_34_03_726_v3.png", "sentence": "She clambered up the steep rocks and continued her walk.", "sentence_trans": "她爬上了陡峭的岩石，然后继续前行。", "sentence_audio": "sa_15_15462_0_3_20150808180133.aac", "cloze_data": "{\"syllable\":\"clam-ber\"", "cloze": "clam-b[er]", "options": "[\"ar|ir|or|ur|a\"]", "tips": "[[\"amb[er]\"", "word_etyma": ""}