{"topic_id": "7325", "word_level_id": "1157", "tag_id": "0", "word": "needy", "word_audio": "us_needy_20231221133307936_a3bca56a3b7d6903d340.mp3", "image_file": "07f8acc0cd64daa1705a7b385b592c12_108121_1671506760.jpg", "accent": "/ˈniːdi/", "mean_cn": "adj.贫困的；贫穷的", "mean_en": "\"(of people) not having enough money", "sentence_phrase": "", "deformation_img": "20140820_23_36_17_348_v3.png", "sentence": "Volunteers are giving food to the needy.", "sentence_trans": "志愿者们正在给穷人提供食物。", "sentence_audio": "us_Volunteers_are_20221220112613471_ec087ebb6a73c2368e2e.mp3", "cloze_data": "{\"syllable\":\"needy\"", "cloze": "n[ee]dy", "options": "[\"ea|ie|ii|ye|e\"]", "tips": "[[]]}", "word_etyma": ""}