{"topic_id": "4639", "word_level_id": "15", "tag_id": "0", "word": "implement", "word_audio": "us_implement_20240516115040859_6e95c8a2f8d83542a896.mp3", "image_file": "implement_4639_20231106_4150f8b7.jpg", "accent": "/ˈɪmplɪment/", "mean_cn": "n.工具，器具；  v.实施，执行", "mean_en": "\"a tool or an instrument", "sentence_phrase": "", "deformation_img": "20130510_18_26_41_1.png", "sentence": "I use these implements to take care of my garden.", "sentence_trans": "我用这些工具来打理我的花园。", "sentence_audio": "sa_1_4639_0_2_20150808122923.aac", "cloze_data": "{\"syllable\":\"im-ple-ment\"", "cloze": "im-[ple]-ment", "options": "[\"tle|ble|dle|gle\"]", "tips": "[[]]}", "word_etyma": "im进 + ple满，填满 + ment指动作本身 → 装入并填满 → implement完成，实施"}