{"topic_id": "3233", "word_level_id": "14", "tag_id": "0", "word": "euphonious", "word_audio": "euphonious.mp3", "image_file": "95eb8f28460049440bc258187883b6aa_98176_1695896162.jpg", "accent": "/juːˈfoʊniəs/", "mean_cn": "adj.声音和谐的；悦耳的", "mean_en": "having a pleasant sound", "sentence_phrase": "beautiful and euphonious", "deformation_img": "20140828_16_27_25_699_v3.png", "sentence": "I love the music; it is so beautiful and euphonious.", "sentence_trans": "我喜欢这音乐，非常优美悦耳。", "sentence_audio": "us_I_love_20230928181607970_114d505a6dce7d24748d.mp3", "cloze_data": "{\"syllable\":\"e-u-pho-nious\"", "cloze": "e-u-ph[o]-ni[ou]s", "options": "[\"a|e|i|u\"", "tips": "[[\"ph[o]\"", "word_etyma": "eu好，优秀+phon声音+ious形容词后缀→声音好听的"}