{"topic_id": "1905", "word_level_id": "14", "tag_id": "0", "word": "mumble", "word_audio": "us_mumble_20231222100645155_0f6aa7cdb7fb6c778f48.mp3", "image_file": "mumble_1905_20231106_724f7c29.jpg", "accent": "/ˈmʌmbl/", "mean_cn": "v.含糊地说；抿着嘴嚼；  n.含糊的话", "mean_en": "to say (something) quietly in an unclear way that makes it difficult for people to know what you said", "sentence_phrase": "", "deformation_img": "20140731_22_15_07_755_v3.png", "sentence": "\"He\\u0027s mumbling in the sleep again", "sentence_trans": "这个男孩又在梦中含糊地说着话，他到底在说什么啊？", "sentence_audio": "cylwttycs2d3e59f9urga9uq6b6vx2ad.mp3", "cloze_data": "{\"syllable\":\"mum-ble\"", "cloze": "mum-[ble]", "options": "[\"tle|dle|ple|cle|gle|kle\"]", "tips": "[[\"ca[ble]\"", "word_etyma": ""}