{"topic_id": "267", "word_level_id": "1157", "tag_id": "0", "word": "avalanche", "word_audio": "us_avalanche_20231212225955914_38c77582c5cc5dd20b9c.mp3", "image_file": "c85b5775c630a9450d44c61e963c6601_69952_1701669905.jpg", "accent": "/ˈævəlæntʃ/", "mean_cn": "n.雪崩", "mean_en": "a large amount of snow and ice or of dirt and rocks that slides suddenly down the side of a mountain", "sentence_phrase": "", "deformation_img": "20140801_13_10_43_983_v3.png", "sentence": "The avalanche buried the small cabin in the snow.", "sentence_trans": "雪崩掩埋了那个小木屋。", "sentence_audio": "us_The_avalanche_20240422151446593_3f16ec7019a5324cd8e5.mp3", "cloze_data": "{\"syllable\":\"avalanche\"", "cloze": "av[al]anche", "options": "[\"el|le|nl|ol\"]", "tips": "[[]]}", "word_etyma": ""}