{"topic_id": "2246", "word_level_id": "14", "tag_id": "0", "word": "repose", "word_audio": "repose.mp3", "image_file": "8f046fc8d068c9c043a113f878b17a69_291970_1701934927.jpg", "accent": "/rɪˈpoʊz/", "mean_cn": "n.休息，睡眠；  vi.建立于…之上；  vt.使休息，使依靠", "mean_en": "a state of resting or not being active", "sentence_phrase": "in repose", "deformation_img": "", "sentence": "My baby is so adorable in repose.", "sentence_trans": "吾儿睡觉的样子真可爱。", "sentence_audio": "sa_14_2246_0_3_20150808153425.aac", "cloze_data": "{\"syllable\":\"re-pose\"", "cloze": "r[e]-pose", "options": "[\"a|i|o|u\"]", "tips": "[[\"r[e]\"", "word_etyma": "re向后，相反 + pose放 → 放下工作 → repose休息"}