{"topic_id": "7307", "word_level_id": "14", "tag_id": "0", "word": "varnish", "word_audio": "us_varnish_20231221095147386_6bcf51394f24b71dd23a.mp3", "image_file": "d36ad744f33da1d5afdd1356863aa40e_162307_1702000561.jpeg", "accent": "/ˈvɑːrnɪʃ/", "mean_cn": "n.清漆；光泽面；  v.使…有光泽", "mean_en": "\"a liquid that is painted onto wood", "sentence_phrase": "two layers of varnish", "deformation_img": "", "sentence": "\"After this layer of paint dries", "sentence_trans": "这层油漆干了以后，我们还需要上两层清漆。", "sentence_audio": "2escjjruc3h6jnq4rwcy8yydbq2mv9yg.mp3", "cloze_data": "{\"syllable\":\"var-nish\"", "cloze": "var-ni[sh]", "options": "[\"tch|chr|sch|th\"]", "tips": "[[\"burni[sh]\"", "word_etyma": ""}