{"topic_id": "5415", "word_level_id": "1157", "tag_id": "0", "word": "kin", "word_audio": "us_kin_20231222111929281_ff221365313c6fd4255b.mp3", "image_file": "102b502589fe9a2747b9c2a1f339a282_92367_1566888845.jpg", "accent": "/kɪn/", "mean_cn": "n.亲属", "mean_en": "your family or your relatives", "sentence_phrase": "", "deformation_img": "", "sentence": "Of course I love them; they\\u0027re my kin.", "sentence_trans": "我当然爱他们，他们是我的亲人。", "sentence_audio": "sa_2_5415_0_3_20150808144812.aac", "cloze_data": "{\"syllable\":\"kin\"", "cloze": "k[in]", "options": "[\"en|on|un|an|e|i|a|o|u\"]", "tips": "[[\"unk[in]\"", "word_etyma": ""}