{"topic_id": "1224", "word_level_id": "15", "tag_id": "0", "word": "fortuitous", "word_audio": "fortuitous.mp3", "image_file": "fortuitous_1224_20231106_d0615801.jpg", "accent": "/fɔːrˈtuːɪtəs/", "mean_cn": "adj.幸运的", "mean_en": "happening by chance", "sentence_phrase": "", "deformation_img": "", "sentence": "It was extremely fortuitous to find a real diamond.", "sentence_trans": "能找到真钻石真是太幸运啦！", "sentence_audio": "3_0_20160720072643_27933_c.aac", "cloze_data": "{\"syllable\":\"for-tu-itous\"", "cloze": "f[or]-tu-itous", "options": "[\"ar|er|ir|ur|a\"]", "tips": "[[\"f[or]ay\"", "word_etyma": "fortuit\\u003dfortune运气 + ous 多...的 → fortuitous偶然的；意外的"}