{"topic_id": "8650", "word_level_id": "1157", "tag_id": "0", "word": "canoe", "word_audio": "931983b90c3ee57a00340c5a4c14e683_43929_1714441422.mp3", "image_file": "e9c9bd0d0e43952abb7099077236e688_80454_1574930638.jpeg", "accent": "/kəˈnuː/", "mean_cn": "n.独木舟，轻舟", "mean_en": "a light narrow boat which you move along in the water with a paddle", "sentence_phrase": "", "deformation_img": "d_107_8650_0_2_20150809023649.png", "sentence": "The red canoe is resting on the shallow water.", "sentence_trans": "这只红色独木舟停靠在浅水滩上。", "sentence_audio": "7cdfef86c1f20dd41cbb1ead7fbc3b68_35230_1574930633.mp3", "cloze_data": "{\"syllable\":\"ca-noe\"", "cloze": "ca-n[oe]", "options": "[\"oa|oi|oy|oo|o\"]", "tips": "[[\"an[oe]sis\"", "word_etyma": ""}