{"topic_id": "4296", "word_level_id": "1157", "tag_id": "0", "word": "foul", "word_audio": "us_foul_20231211162517460_2ad6e20df77b266f5487.mp3", "image_file": "ec5c6a28b97636318707dea1eecfbf7e_81290_1566804541.jpg", "accent": "/faʊl/", "mean_cn": "adj.难闻的，发臭的；糟透了的", "mean_en": "dirty and smelling bad", "sentence_phrase": "", "deformation_img": "20140726_11_27_55_212_v3.png", "sentence": "Ewww—that smells foul!", "sentence_trans": "呃，那个闻起来太臭了。", "sentence_audio": "sa_2_4296_0_3_20150808142936.aac", "cloze_data": "{\"syllable\":\"foul\"", "cloze": "f[oul]", "options": "[\"oar|oor|our|uir\"]", "tips": "[[\"enf[oul]\"", "word_etyma": ""}