{"topic_id": "3394", "word_level_id": "14", "tag_id": "0", "word": "cadge", "word_audio": "cadge.mp3", "image_file": "892df6107880930ef6f765fe61325c77_179248_1699325434.jpg", "accent": "/kædʒ/", "mean_cn": "v.行乞，乞求，贩卖", "mean_en": "to persuade someone to give you (something) for free", "sentence_phrase": "", "deformation_img": "", "sentence": "This homeless man is forced to cadge in the street.", "sentence_trans": "这个无家可归的人被迫在街上乞讨。", "sentence_audio": "us_This_homeless_20231107105456393_5d2ec1bad7dcf485a432.mp3", "cloze_data": "{\"syllable\":\"cadge\"", "cloze": "ca[dge]", "options": "[\"gue|geo|dj|ge\"]", "tips": "[[]]}", "word_etyma": ""}