{"topic_id": "6803", "word_level_id": "1157", "tag_id": "0", "word": "globe", "word_audio": "us_globe_20231213101850458_0e14e8cc5a445f713a89.mp3", "image_file": "i_1_6803_0_3_20150808125512-gigapixel-scale.jpg", "accent": "/ɡloʊb/", "mean_cn": "n.地球，世界", "mean_en": "the world (used especially to emphasize its size)", "sentence_phrase": "", "deformation_img": "d_16_6803_0_2_20150808231058.png", "sentence": "\"Airplanes fly all over the globe", "sentence_trans": "飞机在全世界飞行，甚至会飞过两极上空。", "sentence_audio": "sa_1_6803_0_3_20150808125512.aac", "cloze_data": "{\"syllable\":\"globe\"", "cloze": "glob[e]", "options": "[\"a|i|o|u\"]", "tips": "[[\"inglob[e]\"", "word_etyma": ""}