{"topic_id": "5203", "word_level_id": "1157", "tag_id": "0", "word": "monarch", "word_audio": "us_phoneme_alphabetipa_20240223142253642_f191cc711de385b1535d.mp3", "image_file": "82dab9e9caaf66a47af6e5cf99d15906_52296_1701068469.jpg", "accent": "/ˈmɑːnərk/", "mean_cn": "n.君主，帝王", "mean_en": "\"a person who rules a country", "sentence_phrase": "", "deformation_img": "20140718_18_51_03_436_v3.png", "sentence": "This actor portrayed a renowned monarch in history.", "sentence_trans": "这位演员扮演了历史上一位著名的君主。", "sentence_audio": "us_This_actor_20240201131003232_2d9014f604e0a078c4ee.mp3", "cloze_data": "{\"syllable\":\"monarch\"", "cloze": "mon[ar]ch", "options": "[\"er|ir|or|ur|a\"]", "tips": "[[\"archmon[ar]ch\"", "word_etyma": "mon单个，一个 + arch统治者 → 一个统治者 → monarch君主，独裁者"}