{"topic_id": "1787", "word_level_id": "1157", "tag_id": "0", "word": "magnify", "word_audio": "us_magnify_20231219115031254_022d037f3cf524dc70aa.mp3", "image_file": "i_2_1787_0_8_151220013114-gigapixel-scale.jpg", "accent": "/ˈmæɡnɪfaɪ/", "mean_cn": "v.放大，扩大", "mean_en": "\"to make something look bigger than it really is", "sentence_phrase": "", "deformation_img": "20140630_12_01_11_233_v3.png", "sentence": "He needs to magnify the objects so he can see them better.", "sentence_trans": "他需要放大物体以便能够看清它们。", "sentence_audio": "sa_2_1787_0_8_151223162549.aac", "cloze_data": "{\"syllable\":\"mag-ni-fy\"", "cloze": "mag-n[i]-fy", "options": "[\"a|e|o|u\"]", "tips": "[[\"Bin[i]\"", "word_etyma": "magni大 + fy使… → magnify放大，扩大"}