{"topic_id": "15551", "word_level_id": "14", "tag_id": "0", "word": "scurvy", "word_audio": "scurvy.mp3", "image_file": "f9c49a0b5548898b82a773b1efd97e6f_84541_1705305390.jpg", "accent": "/ˈskɜːrvi/", "mean_cn": "n.坏血病；  adj.卑鄙的，下流的", "mean_en": "a disease that is caused by not eating enough fruits or vegetables that contain vitamin C", "sentence_phrase": "", "deformation_img": "", "sentence": "Scurvy causes bleeding in the gums.", "sentence_trans": "坏血病会导致牙龈出血。", "sentence_audio": "us_Scurvy_causes_20240115155634302_0fca3b9610178d26111a.mp3", "cloze_data": "{\"syllable\":\"scurvy\"", "cloze": "sc[ur]vy", "options": "[\"ar|er|ir|or|a\"]", "tips": "[[\"sc[ur]vyweed\"]]}", "word_etyma": ""}