{"topic_id": "17758", "word_level_id": "1157", "tag_id": "0", "word": "admiral", "word_audio": "admiral.mp3", "image_file": "3_0_20160718113654_87721_c.jpg", "accent": "/ˈædmərəl/", "mean_cn": "n.海军上将", "mean_en": "a high-ranking officer in the navy", "sentence_phrase": "", "deformation_img": "", "sentence": "\"After the great admiral set sail with his fleet", "sentence_trans": "海军将领郑和率领舰队启航下西洋后，中国统治了海洋。", "sentence_audio": "b2712c5419f7cad0_1266883482406771214_250207.mp3", "cloze_data": "{\"syllable\":\"ad-mi-ral\"", "cloze": "ad-mi-r[al]", "options": "[\"el|le|nl|ol\"]", "tips": "[[\"or[al]\"", "word_etyma": ""}