{"topic_id": "1040", "word_level_id": "12", "tag_id": "0", "word": "ensue", "word_audio": "us_ensue_20231220110233746_0c47ed811c16c726acc8.mp3", "image_file": "i_2_1040_0_4_20150808141406-gigapixel-scale.jpg", "accent": "/ɪnˈsuː/", "mean_cn": "v.跟着发生，接踵而来", "mean_en": "to happen after or as a result of another event", "sentence_phrase": "", "deformation_img": "20140815_17_17_44_873_v3.png", "sentence": "Landslide ensued after the storm.", "sentence_trans": "风暴之后，滑坡接踵而至。", "sentence_audio": "us_Landslide_ensued_20230116153403647_a9e47ec62d4ae42450b3.mp3", "cloze_data": "{\"syllable\":\"en-sue\"", "cloze": "en-s[ue]", "options": "[\"uu|ua|ui|uo|iu|u\"]", "tips": "[[\"s[ue]\"", "word_etyma": ""}