{"topic_id": "10815", "word_level_id": "14", "tag_id": "0", "word": "fateful", "word_audio": "us_fateful_20240902140423715_457dd7a7f2fbb31ef59d.mp3", "image_file": "fateful_10815_20231106_98ca7f11.jpg", "accent": "/ˈfeɪtfl/", "mean_cn": "adj.决定性的", "mean_en": "\"having an important", "sentence_phrase": "", "deformation_img": "", "sentence": "The Qing government made the fateful decision to adopt a closed-door policy.", "sentence_trans": "清政府做出了一项重大的决定——闭关锁国。", "sentence_audio": "us_The_Qing_20241009151626219_70ee246e78c15929f35c.mp3", "cloze_data": "{\"syllable\":\"fate-ful\"", "cloze": "fate-f[u]l", "options": "[\"a|e|i|o\"]", "tips": "[[\"awf[u]l\"", "word_etyma": "fate宿命 + ful形容词后缀 → fateful宿命的，重大的"}