{"topic_id": "15032", "word_level_id": "15", "tag_id": "0", "word": "wanton", "word_audio": "c675e949a4e42577ae4e177fcae21aea_18887_1524899003.mp3", "image_file": "0c324fc8a2da2b6a5369fa8bab657917_135681_1524139519.jpg", "accent": "/ˈwɑːntən/", "mean_cn": "adj.胡作非为的，淫荡的，无节制的；  n.水性杨花的人，任性的孩子，无节制的人；  v.放肆，胡作非为，挥霍", "mean_en": "not limited or controlled", "sentence_phrase": "", "deformation_img": "", "sentence": "What they are doing is absolute wanton destruction to our planet!", "sentence_trans": "他们这样做完全是对地球肆意的破坏！", "sentence_audio": "66fa9d6f10e65bcf7881af1a1a2d0b74_39323_1524898985.mp3", "cloze_data": "{\"syllable\":\"wan-ton\"", "cloze": "w[an]-ton", "options": "[\"en|in|on|un|e|i|a|o|u\"]", "tips": "[[\"w[an]\"", "word_etyma": ""}