{"topic_id": "16158", "word_level_id": "14", "tag_id": "0", "word": "valiant", "word_audio": "valiant.mp3", "image_file": "a014d8d5093d137b8640f8a9a32fb67a_112820_1696644654.jpg", "accent": "/ˈvæliənt/", "mean_cn": "adj.勇敢的，英勇的；  n.勇士，勇敢的人", "mean_en": "having or showing courage :very brave or courageous", "sentence_phrase": "valiant knight", "deformation_img": "20140826_17_59_52_411_v3.png", "sentence": "His ambition is to become a valiant knight and rid the world of evil.", "sentence_trans": "他的梦想是成为一名勇敢的骑士消除世界的邪恶。", "sentence_audio": "us_His_ambition_20231007101106313_58edf96979f271b07ce6.mp3", "cloze_data": "{\"syllable\":\"valiant\"", "cloze": "v[al]iant", "options": "[\"el|le|nl|ol\"]", "tips": "[[\"v[al]iantly\"", "word_etyma": "vali\\u003dval\\u003dpower强壮 ＋ ant形容词后缀 → valiant勇敢的"}