{"topic_id": "7482", "word_level_id": "12", "tag_id": "0", "word": "counterfeit", "word_audio": "us_counterfeit_20231219112941003_64ce03546dd6c029ab18.mp3", "image_file": "c_20150525_094047_4_7482-gigapixel-scale.jpg", "accent": "/ˈkaʊntərfɪt/", "mean_cn": "v.伪造，仿造；  n.仿制品，伪造物；  adj.仿造的，假冒的", "mean_en": "to make an exact copy of something in order to trick people into thinking that it is the real thing", "sentence_phrase": "", "deformation_img": "20140820_22_03_33_218_v3.png", "sentence": "She counterfeits a zebra by painting on a donkey.", "sentence_trans": "她给驴子涂上颜色来冒充斑马。", "sentence_audio": "us_She_counterfeits_20240122131052890_aa251cafd96ed7bbaaa1.mp3", "cloze_data": "{\"syllable\":\"coun-ter-feit\"", "cloze": "coun-t[er]-feit", "options": "[\"ar|ir|or|ur|a\"]", "tips": "[[\"alt[er]\"", "word_etyma": "counter相反 ＋ feit\\u003ddo做 → 做（与真品）相反的 → counterfeit假冒的"}