{"topic_id": "15539", "word_level_id": "15", "tag_id": "0", "word": "spurious", "word_audio": "783c87a0908b0c0f4ac91136b08bb743_20628_1524822720.mp3", "image_file": "11c26e99909ccfa81e8a4aeacd57400c_52747_1524140076.jpg", "accent": "/ˈspjʊriəs/", "mean_cn": "adj.假的，伪造的，欺骗的", "mean_en": "\"not genuine", "sentence_phrase": "", "deformation_img": "", "sentence": "I can tell you for certain that this APP is spurious.", "sentence_trans": "我可以肯定地告诉你这个软件是山寨的。", "sentence_audio": "eba0729541db9e30ac801ec9380dc74f_33888_1524140055.mp3", "cloze_data": "{\"syllable\":\"spu-ri-ous\"", "cloze": "spu-ri-[ou]s", "options": "[\"ae|ao|au|eu|ow|a|o\"]", "tips": "[[\"ay[ou]s\"", "word_etyma": ""}