{"topic_id": "10923", "word_level_id": "14", "tag_id": "0", "word": "lax", "word_audio": "us_lax_20231213100346062_04a6e61b9ae5f9ae0b8a.mp3", "image_file": "lax_10923_20231106_df2590dd.jpg", "accent": "/læks/", "mean_cn": "adj.松懈的；[语]松弛元音的；  n.松元音", "mean_en": "\"not strict", "sentence_phrase": "", "deformation_img": "", "sentence": "The security guard\\u0027s lax attitude towards his work endangers us all.", "sentence_trans": "保安对工作松懈的态度使我们所有人都处于危险之中。", "sentence_audio": "sa_106_10923_0_2_20150809075226.aac", "cloze_data": "{\"syllable\":\"lax\"", "cloze": "l[a]x", "options": "[\"e|i|o|u\"]", "tips": "[[\"l[a]xly\"", "word_etyma": "lax\\u003dloose松 → lax松弛的"}