{"topic_id": "2130", "word_level_id": "12", "tag_id": "0", "word": "prodigious", "word_audio": "us_prodigious_20231226095327851_b5665549e3a8fb4b8557.mp3", "image_file": "421415c56f9ed1f82c3ac141319db9c8_93199_1706677443.jpeg", "accent": "/prəˈdɪdʒəs/", "mean_cn": "adj.巨大的，惊人的", "mean_en": "very large or powerful and causing surprise or admiration", "sentence_phrase": "", "deformation_img": "20140807_19_01_52_93_v3.png", "sentence": "This young girl shows prodigious talent in ballet.", "sentence_trans": "这个年轻女孩在芭蕾舞方面表现出惊人的天赋。", "sentence_audio": "us_This_young_20240131130407898_17435f3fd2ef13e2844e.mp3", "cloze_data": "{\"syllable\":\"prodi-gious\"", "cloze": "prodi-gi[ou]s", "options": "[\"ae|ao|au|eu|ow|a|o\"]", "tips": "[[\"oragi[ou]s\"", "word_etyma": "pro向前，在前 + dig做 + ious形容词后缀 → 做在前面，做得多→ 大量的"}