{"topic_id": "2253", "word_level_id": "15", "tag_id": "0", "word": "reputable", "word_audio": "us_reputable_20231220102227127_37c3264966fd4121435a.mp3", "image_file": "e80409e249adcc81aafd63bb0cbdb01a_89759_1586695160.jpg", "accent": "/ˈrepjətəbl/", "mean_cn": "adj.卓越的；声誉好的", "mean_en": "", "sentence_phrase": "", "deformation_img": "", "sentence": "They want to buy their car through a reputable dealer.", "sentence_trans": "他们想通过一位声誉好的经销商购车。", "sentence_audio": "b8d0cec3e01ef2d6668dcf9ebe4ea324_45684_1586695158.mp3", "cloze_data": "{\"syllable\":\"rep-utable\"", "cloze": "rep-uta[ble]", "options": "[\"tle|dle|ple|cle|gle|kle\"]", "tips": "[[\"deputa[ble]\"", "word_etyma": "re再 + put认为 + able具有某种性质的 → reputable声誉好的"}