{"topic_id": "8669", "word_level_id": "14", "tag_id": "0", "word": "irrigate", "word_audio": "us_irrigate_20231212144344757_dcf3aa480d6ea63bfaa1.mp3", "image_file": "0833d66d4ac9a14efa973cb05fcb2c2e_99323_1576122529.jpeg", "accent": "/ˈɪrɪɡeɪt/", "mean_cn": "v.灌溉，冲洗", "mean_en": "to supply water to an area of land through pipes or channels so that crops will grow", "sentence_phrase": "", "deformation_img": "d_107_8669_0_2_20150809023705.png", "sentence": "The grass is irrigated by the automatic watering system.", "sentence_trans": "这片草地由自动浇灌系统进行灌溉。", "sentence_audio": "ec9807afd8787b2cdf0214e5332490e1_43006_1576122526.mp3", "cloze_data": "{\"syllable\":\"ir-ri-gate\"", "cloze": "[ir]ri-gate", "options": "[\"ar|er|or|ur|a\"]", "tips": "[[\"[ir]rigant\"", "word_etyma": "ir使…成为，进入 + rig船桅装置 + ate动词后缀 → 水进船 → irrigate灌入水，灌溉"}