{"topic_id": "15087", "word_level_id": "14", "tag_id": "0", "word": "depose", "word_audio": "depose.mp3", "image_file": "690f60b912623bbfef136ec31b93a1af_123230_1694063633.jpg", "accent": "/dɪˈpoʊz/", "mean_cn": "v.免职，废黜，作证", "mean_en": "to remove (someone) from a powerful position", "sentence_phrase": "", "deformation_img": "", "sentence": "He has been deposed and lost his official position.", "sentence_trans": "他被罢免了，丢了乌纱帽。", "sentence_audio": "3_0_20160911070839_91418_c.aac", "cloze_data": "{\"syllable\":\"de-pose\"", "cloze": "d[e]-pose", "options": "[\"a|i|o|u\"]", "tips": "[[\"d[e]\"", "word_etyma": "de去掉 + pose位置 → depose 免职"}