{"topic_id": "15421", "word_level_id": "15", "tag_id": "0", "word": "purveyor", "word_audio": "purveyor.mp3", "image_file": "20120524_12_54_12_729.jpg", "accent": "/pərˈveɪər/", "mean_cn": "n.供应粮食者", "mean_en": "a person or business that sells or provides something", "sentence_phrase": "a purveyor of fine foods", "deformation_img": "", "sentence": "We are a purveyor of fine foods to discerning clients.", "sentence_trans": "我们是为有鉴赏力的客户提供美食的供应商。", "sentence_audio": "us_We_are_20241009154656000_5c121514bd46e6e108ce.mp3", "cloze_data": "{\"syllable\":\"pur-vey-or\"", "cloze": "p[ur]-vey-or", "options": "[\"ar|er|ir|or|a\"]", "tips": "[[\"p[ur]dy\"", "word_etyma": "purvey供给 ＋ or表示人 → purveyor承办商；伙食承办商"}