{"topic_id": "5989", "word_level_id": "14", "tag_id": "0", "word": "tender", "word_audio": "us_tender_20231218134307154_6ef349a687cd7cd7153a.mp3", "image_file": "57dee93d63539ad906acb0ad9197476d_63195_1565342778.jpg", "accent": "/ˈtendər/", "mean_cn": "adj.温柔的；柔弱的，脆弱的；  n.煤水车；  v.提出（希望对方接受的意见等）", "mean_en": "\"kind", "sentence_phrase": "", "deformation_img": "d_14_5989_0_2_20150808162813.png", "sentence": "You have to be soft and tender with the baby.", "sentence_trans": "你得对婴儿温柔呵护。", "sentence_audio": "d97d14f3f92c8edad730641ed5a02cab_13054_1538651389.mp3", "cloze_data": "{\"syllable\":\"ten-der\"", "cloze": "ten-d[er]", "options": "[\"ar|ir|or|ur|a\"]", "tips": "[[\"d[er]by\"", "word_etyma": "tend伸，伸出 + er形容词后缀 → 刚伸出的嫩芽 → tender嫩的，柔软的，温柔的"}