{"topic_id": "14979", "word_level_id": "12", "tag_id": "0", "word": "hazard", "word_audio": "us_hazard_20231212144156438_2fcbb52142db6fdbc4d1.mp3", "image_file": "aad93470d00de5fa0fb9b49c24024cf9_188908_1561953060.jpg", "accent": "/ˈhæzərd/", "mean_cn": "n.危险；公害；危险的事物；机会；  v.使冒险，冒险做", "mean_en": "a thing that can be dangerous or cause damage", "sentence_phrase": "", "deformation_img": "20130518_03_13_42_827.png", "sentence": "\"In big cities", "sentence_trans": "在大城市里，我们总是有很多道路危险要注意。", "sentence_audio": "2ecae9a1a4d62b8382e33a03bb9dead2_33590_1561953060.mp3", "cloze_data": "{\"syllable\":\"haz-ard\"", "cloze": "haz-[ar]d", "options": "[\"er|ir|or|ur|a\"]", "tips": "[[\"cow[ar]d\"", "word_etyma": ""}