{"topic_id": "8216", "word_level_id": "1157", "tag_id": "0", "word": "protocol", "word_audio": "us_protocol_20230704131341063_f91e2a4c84accb4e27d7.mp3", "image_file": "598143cf48ee498e554377162d06c5fc_92945_1679389439-800-600.jpg", "accent": "/ˈproʊtəˌkɔl/", "mean_cn": "n.外交礼节", "mean_en": "a system of rules that explain the correct conduct and procedures to be followed in formal situations", "sentence_phrase": "", "deformation_img": "", "sentence": "\"When presidents meet", "sentence_trans": "当总统们会面的时候，外交礼节规定他们必须握手。", "sentence_audio": "20e469208baea7c14d0a64358a54095b_40746_1522661459.mp3", "cloze_data": "{\"syllable\":\"pro-to-col\"", "cloze": "pro-to-c[ol]", "options": "[\"al|el|le|nl\"]", "tips": "[[\"c[ol]in\"", "word_etyma": "proto最早的 + col胶 → protocol外交礼节"}