{"topic_id": "11405", "word_level_id": "12", "tag_id": "0", "word": "cult", "word_audio": "us_cult_20230705164204795_09316a8e92b438729c9d.mp3", "image_file": "f72722557ff2e8e968c80bc58e3dd8e7_161327_1570872323.jpeg", "accent": "/kʌlt/", "mean_cn": "n.异教；风尚，热潮；信徒；  adj.流行的；风靡一时的", "mean_en": "a small group of people who have extreme religious beliefs and who are not part of any established religion", "sentence_phrase": "", "deformation_img": "", "sentence": "Believers of this cult worship aliens.", "sentence_trans": "这个异教的教徒崇拜外星人。", "sentence_audio": "c1bd73f7efd60b7803b0ecd5a5b8de43_24403_1570872321.mp3", "cloze_data": "{\"syllable\":\"cult\"", "cloze": "c[u]lt", "options": "[\"a|e|i|o\"]", "tips": "[[\"ausc[u]lt\"", "word_etyma": ""}