{"topic_id": "8608", "word_level_id": "1157", "tag_id": "0", "word": "melody", "word_audio": "melody.mp3", "image_file": "3_0_20160724070759_74751_c-gigapixel-scale.jpg", "accent": "/ˈmelədi/", "mean_cn": "n.旋律，悦耳的音乐", "mean_en": "\"a tune", "sentence_phrase": "", "deformation_img": "20140719_23_15_00_797_v3.png", "sentence": "He played a beautiful melody on the piano.", "sentence_trans": "他用钢琴弹奏了一段美妙的旋律。", "sentence_audio": "3_0_20160724070759_22516_c.aac", "cloze_data": "{\"syllable\":\"melody\"", "cloze": "m[el]ody", "options": "[\"al|le|nl|ol\"]", "tips": "[[\"m[el]odyless\"", "word_etyma": "mel[\\u003d希腊文melos歌曲] + ody歌曲 → 歌唱歌曲 → melody旋律"}