{"topic_id": "391350", "word_level_id": "1157", "tag_id": "0", "word": "empirical", "word_audio": "us_empirical_20231219112144656_050b01e0675e39d157dc.mp3", "image_file": "390b00768eb6732280e9833b2351df70_180342_1596005918.jpeg", "accent": "/ɪmˈpɪrɪkəl/", "mean_cn": "adj.实证的，以观察或实验为根据的", "mean_en": "based on experiments or experience rather than ideas or theories", "sentence_phrase": "", "deformation_img": "", "sentence": "Empirical studies focus more on observation rather than theory alone.", "sentence_trans": "实证研究更强调观察而非理论本身。", "sentence_audio": "59208ac9755e22b682421ecdd536cf39_45598_1596005919.mp3", "cloze_data": "", "cloze": "", "options": "", "tips": "", "word_etyma": "em在...中 + piri实验，试验 + cal形容词后缀 → empirical实证的，以实验为根据的"}