{"topic_id": "8220", "word_level_id": "1157", "tag_id": "0", "word": "blanket", "word_audio": "us_blanket_20231212134639983_331c5183b2ecf53b2cfd.mp3", "image_file": "eb9f15447b1ee42ee6749a291dd8332e_152183_1544067498.jpeg", "accent": "/ˈblæŋkɪt/", "mean_cn": "n.毯子", "mean_en": "\"a large cover", "sentence_phrase": "", "deformation_img": "d_16_8220_0_2_20150808232723.png", "sentence": "The cute little kitten is sleeping in a soft blanket.", "sentence_trans": "那只可爱的小猫正睡在一条柔软的毯子里。", "sentence_audio": "jrncgjhcac3z7huseuxwtuyaqrknht2u.mp3", "cloze_data": "{\"syllable\":\"blan-ket\"", "cloze": "bl[an]-ket", "options": "[\"en|in|on|un|e|i|a|o|u\"]", "tips": "[[\"bl[an]\"", "word_etyma": "blank\\u003dblanc白 ＋ et表名词 → 白色织物 → blanket毛毯，毯子，羊毛毯"}