{"topic_id": "15480", "word_level_id": "15", "tag_id": "0", "word": "implacable", "word_audio": "implacable.mp3", "image_file": "fdddf728421a98c62e54a796fbbb5b51_151383_1543904074.jpeg", "accent": "/ɪmˈplækəbl/", "mean_cn": "adj.不饶人的", "mean_en": "opposed to someone or something in a very angry or determined way that cannot be changed", "sentence_phrase": "", "deformation_img": "20140904_02_32_08_530_v3.png", "sentence": "The cat and fish are implacable enemies.", "sentence_trans": "鱼和猫是死敌。", "sentence_audio": "d4a0acc3b6783f4ef8a9d451eda84946_12113_1543904082.mp3", "cloze_data": "{\"syllable\":\"im-placa-ble\"", "cloze": "im-placa-[ble]", "options": "[\"tle|dle|ple|cle|gle|kle\"]", "tips": "[[\"ca[ble]\"", "word_etyma": "im不 ＋ plac使平静 ＋ able能…的 → implacable不平静的；难以安慰的"}