{"topic_id": "10873", "word_level_id": "15", "tag_id": "0", "word": "incapacitate", "word_audio": "incapacitate.mp3", "image_file": "incapacitate_10873_20231106_3eee8992.jpg", "accent": "/ˌɪnkəˈpæsɪteɪt/", "mean_cn": "v.使瘫痪；使不能；使无能力；使不适合", "mean_en": "\"to deprive of power", "sentence_phrase": "incapacitated her from", "deformation_img": "", "sentence": "The accident incapacitated her from dancing.", "sentence_trans": "这场事故使她不能跳舞了。", "sentence_audio": "3_0_20160724071126_55699_c.aac", "cloze_data": "{\"syllable\":\"in-ca-pa-ci-tate\"", "cloze": "[in]-ca-p[a]-ci-tate", "options": "[\"en|on|un|an|e|i|a|o|u\"", "tips": "[[\"[in]\"", "word_etyma": "in不，无， ＋ capacit能够 ＋ ate使之成... → incapacitate使无能力；使不能；使不适于"}