{"topic_id": "15882", "word_level_id": "12", "tag_id": "0", "word": "inherited", "word_audio": "wa_12_15882_0_2_20150808184125.aac", "image_file": "9d375a916bc714181a94478359c3765f_375878_1722221493.jpg", "accent": "/ɪnˈherɪtɪd/", "mean_cn": "adj.遗传的（病等），继承权的，通过继承得到的", "mean_en": "tending to occur among members of a family usually by heredity", "sentence_phrase": "", "deformation_img": "", "sentence": "Color blind is a type of inherited disease.", "sentence_trans": "色盲是一种遗传病。", "sentence_audio": "us_Color_blind_20240729105045738_ea8843d9ab3583927bb3.mp3", "cloze_data": "", "cloze": "", "options": "", "tips": "", "word_etyma": "inherit继承 ＋ ed形容词后缀 → inherited遗传的"}