{"topic_id": "11398", "word_level_id": "12", "tag_id": "0", "word": "laurel", "word_audio": "laurel.mp3", "image_file": "i_12_11398_0_2_20150808181751.jpg", "accent": "/ˈlɔːrəl/", "mean_cn": "n.月桂树，桂冠，殊荣", "mean_en": "an evergreen tree or bush with shiny pointed leaves", "sentence_phrase": "laurel leaves", "deformation_img": "", "sentence": "\"In the ancient Olympic Games", "sentence_trans": "在古代奥林匹克运动会中，获胜者被赠与月桂树叶做成的桂冠。", "sentence_audio": "sa_12_11398_0_2_20150808181751.aac", "cloze_data": "{\"syllable\":\"Lau-rel\"", "cloze": "Lau-r[el]", "options": "[\"al|le|nl|ol\"]", "tips": "[[\"bur[el]\"", "word_etyma": ""}