{"topic_id": "15825", "word_level_id": "12", "tag_id": "0", "word": "liquidator", "word_audio": "liquidator.mp3", "image_file": "20120807_03_32_47_987.jpg", "accent": "/ˈlɪkwɪdeɪtər/", "mean_cn": "n.清算人", "mean_en": "(law) a person (usually appointed by a court of law) who liquidates assets or preserves them for the benefit of affected parties", "sentence_phrase": "", "deformation_img": "", "sentence": "Our house was repossessed and sold by a liquidator.", "sentence_trans": "我们的房屋被清算人重新占有并出售。", "sentence_audio": "sa_12_15825_0_2_20150808183709.aac", "cloze_data": "{\"syllable\":\"liq-uida-tor\"", "cloze": "liq-uida-t[or]", "options": "[\"ar|er|ir|ur|a\"]", "tips": "[[\"t[or]\"", "word_etyma": ""}