{"topic_id": "4156", "word_level_id": "12", "tag_id": "0", "word": "bargain", "word_audio": "us_bargain_20231222094312139_0031bd718adeadd5d539.mp3", "image_file": "e52d4232b1ca30eceaed45ebd57a1963_137097_1701049238.jpg", "accent": "/ˈbɑːrɡən/", "mean_cn": "v.讨价还价；经讨价还价成交；  n.交易；便宜货；契约", "mean_en": "\"to discuss prices", "sentence_phrase": "", "deformation_img": "d_16_4156_0_2_20150808224039.png", "sentence": "The lady is trying to bargain with the seller.", "sentence_trans": "这位女士试图和卖方砍价。", "sentence_audio": "bacc6ssrekgmqxanbrcfdvx393x26w3a.mp3", "cloze_data": "{\"syllable\":\"bar-gain\"", "cloze": "b[ar]-gain", "options": "[\"er|ir|or|ur|a\"]", "tips": "[[\"b[ar]\"", "word_etyma": ""}