{"topic_id": "10034", "word_level_id": "15", "tag_id": "0", "word": "tundra", "word_audio": "tundra.mp3", "image_file": "tundra_10034_20231106_95814ae8.jpg", "accent": "/ˈtʌndrə/", "mean_cn": "n.冻土地带", "mean_en": "a large area of flat land in northern parts of the world where there are no trees and the ground is always frozen", "sentence_phrase": "northern tundra", "deformation_img": "", "sentence": "Not many animals can live in the frozen northern tundra.", "sentence_trans": "很少有动物能在北方冻土地带生存。", "sentence_audio": "px3jj4rr8q2j9lakvnaullnzuas4ptf3.mp3", "cloze_data": "{\"syllable\":\"tun-dra\"", "cloze": "t[un]-dra", "options": "[\"en|in|on|an|e|i|a|o|u\"]", "tips": "[[\"alt[un]\"", "word_etyma": ""}