{"topic_id": "5196", "word_level_id": "1157", "tag_id": "0", "word": "hay", "word_audio": "us_hay_20231221132530358_bf6915e5131cd4fcb24e.mp3", "image_file": "3_66_20170630170234_6941_c-gigapixel-scale.jpg", "accent": "/heɪ/", "mean_cn": "n.干草", "mean_en": "grass that has been cut and dried and is used as food for animals", "sentence_phrase": "", "deformation_img": "d_16_5196_0_5_20150808225127.png", "sentence": "The cows are hungry—bring them some hay to eat.", "sentence_trans": "这些牛很饿——给它们喂一些干草吃吧。", "sentence_audio": "sa_103_5196_0_3_20150809013503.aac", "cloze_data": "{\"syllable\":\"hay\"", "cloze": "h[ay]", "options": "[\"aa|ai|ei|aw|ey|a\"]", "tips": "[[\"bah[ay]\"", "word_etyma": ""}