{"topic_id": "15094", "word_level_id": "14", "tag_id": "0", "word": "drone", "word_audio": "drone.mp3", "image_file": "96d4cd2dd61c7ed4913ef05850034a19_357764_1616230656.jpg", "accent": "/droʊn/", "mean_cn": "n.无人机；雄蜂；单调的低音；  v.嗡嗡地响", "mean_en": "a type of aircraft with no pilot and is controlled by people on the ground", "sentence_phrase": "", "deformation_img": "20140830_00_10_29_866_v3.png", "sentence": "The drone can deliver your package to the front door of your home.", "sentence_trans": "无人机可以把包裹送到你家门口。", "sentence_audio": "ez88zkvyhst3s955lkq99z3nl46m5lnr.mp3", "cloze_data": "{\"syllable\":\"drone\"", "cloze": "dr[on]e", "options": "[\"en|in|un|an|e|i|a|o|u\"]", "tips": "[[\"hydr[on]e\"", "word_etyma": ""}