{"topic_id": "8071", "word_level_id": "1157", "tag_id": "0", "word": "shrine", "word_audio": "us_shrine_20231113103842446_c2eac4ec1210f7f7ef17.mp3", "image_file": "f004204ae6d34b72280731cd829e9865_199280_1699843024.jpg", "accent": "/ʃraɪn/", "mean_cn": "n.神殿，神祠，圣地", "mean_en": "a place where people come to worship because it is connected with a holy person or event; a place that people visit because it is connected with somebody/something that is important to them", "sentence_phrase": "", "deformation_img": "20140908_16_32_25_697_v3.png", "sentence": "People will bow down before the shrine.", "sentence_trans": "人们会在神龛前鞠躬示敬。", "sentence_audio": "us_People_will_20231113103838670_e078c51ae9c949d4eb51.mp3", "cloze_data": "{\"syllable\":\"Shrine\"", "cloze": "Shr[in]e", "options": "[\"en|on|un|an|e|i|a|o|u\"]", "tips": "[[]]}", "word_etyma": ""}