{"topic_id": "3625", "word_level_id": "14", "tag_id": "0", "word": "pulverize", "word_audio": "us_pulverize_20231026104718468_adec916d5477b7f6d541.mp3", "image_file": "ab8c3018ca2322ad892ec6cda3ca7966_69143_1698288451.jpg", "accent": "/ˈpʌlvəraɪz/", "mean_cn": "v.彻底毁坏；彻底击败", "mean_en": "\"to crush", "sentence_phrase": "pulverized in the crash", "deformation_img": "20140822_22_43_39_157_v3.png", "sentence": "The car was totally pulverized in the crash.", "sentence_trans": "这辆车在这场撞击中完全被摧毁了。", "sentence_audio": "us_The_car_20231026104734997_c1d54ada0cee801c9f10.mp3", "cloze_data": "{\"syllable\":\"pul-ver-ize\"", "cloze": "pul-v[er]-ize", "options": "[\"ar|ir|or|ur|a\"]", "tips": "[[\"v[er]by\"", "word_etyma": "pulver粉末 + ize...化 → pulverize把...弄粉碎"}