{"topic_id": "3726", "word_level_id": "14", "tag_id": "0", "word": "grandiloquent", "word_audio": "grandiloquent.mp3", "image_file": "f6688cb6a452f8aa288fcee6535d9b4c_78506_1695892611.jpg", "accent": "/ɡrænˈdɪləkwənt/", "mean_cn": "adj.（语言等）夸张的，夸大的", "mean_en": "using words that are intended to sound very impressive and important", "sentence_phrase": "delivered a grandiloquent speech", "deformation_img": "", "sentence": "\"The speaker delivered a grandiloquent speech", "sentence_trans": "这位讲者夸夸而谈，用了很多华丽的辞藻。", "sentence_audio": "us_The_speaker_20230928171703402_a51f180a20233e09367b.mp3", "cloze_data": "{\"syllable\":\"grandi-lo-quent\"", "cloze": "grandi-lo-[que]nt", "options": "[\"kn|ng|nk|ck\"]", "tips": "[[\"se[que]nt\"", "word_etyma": "grand宏伟的 + i + loqu说 + ent形容词后缀 → grandiloquent 夸大的"}