{"topic_id": "17042", "word_level_id": "15", "tag_id": "0", "word": "peremptory", "word_audio": "us_peremptory_20240812130530340_3330ae00cc1def916d96.mp3", "image_file": "d6b882416ee3e4903dde67a9b2234bbc_46759_1703745496.jpg", "accent": "/pəˈremptəri/", "mean_cn": "adj.专横的，不容反抗的", "mean_en": "having or showing the insulting attitude of people who think that they should be obeyed without question", "sentence_phrase": "", "deformation_img": "8992af0bca2932abd4fbfba6781971b4_71060_1551843438.png", "sentence": "\"My boss is incredibly peremptory", "sentence_trans": "我的老板如此专横，经常对员工指手画脚。", "sentence_audio": "us_My_boss_20231228143824742_0bd327b65b839866bb51.mp3", "cloze_data": "{\"syllable\":\"peremp-to-ry\"", "cloze": "p[ere]mp-to-ry", "options": "[\"are|ire|ore|ure\"]", "tips": "[[\"p[ere]mptorily\"", "word_etyma": "\"per全部+empt拿，获得+ory...的→专横的"}