{"topic_id": "6205", "word_level_id": "12", "tag_id": "0", "word": "perception", "word_audio": "us_perception_20231219110203031_3a4a0b943fc5444af9f1.mp3", "image_file": "350b4c7af43023f2e086f25f3ce2c864_149381_1538583175.jpg", "accent": "/pərˈsepʃn/", "mean_cn": "n.洞察力，理解力", "mean_en": "\"the way you notice things", "sentence_phrase": "", "deformation_img": "d_1_6205_0_3_20150808124826.png", "sentence": "Perception is the reflection of intelligence.", "sentence_trans": "洞察力是智力的体现。", "sentence_audio": "ac6990e8ec424c8b6f89117b5d127339_13995_1538583201.mp3", "cloze_data": "{\"syllable\":\"per-cep-tion\"", "cloze": "per-cep-t[ion]", "options": "[\"ing|ang|ong|ung\"]", "tips": "[[\"act[ion]\"", "word_etyma": "percept认知 + ion名词后缀 → perception知觉，看法"}