{"topic_id": "4740", "word_level_id": "1157", "tag_id": "0", "word": "erect", "word_audio": "us_erect_20241122140424369_ff89a34cd7fe1cf9466e.mp3", "image_file": "i_1_4740_0_8_160330091228-gigapixel-scale.jpg", "accent": "/ɪˈrekt/", "mean_cn": "v.建造，建立", "mean_en": "to build something; to put something in position and make it stand vertical", "sentence_phrase": "", "deformation_img": "d_1_4740_0_3_20150808122945.png", "sentence": "The workers are busy erecting the building.", "sentence_trans": "工人们正忙于建房子。", "sentence_audio": "cd501eb89c759f3a_1266883529102940806_250207.mp3", "cloze_data": "{\"syllable\":\"erect\"", "cloze": "[ere]ct", "options": "[\"are|ire|ore|ure\"]", "tips": "[[\"[ere]cting\"", "word_etyma": "e向外，向上 + rect指领 → erect建立"}