{"topic_id": "282", "word_level_id": "15", "tag_id": "0", "word": "baffle", "word_audio": "us_baffle_20231213093045942_65b574793530d15b2bbd.mp3", "image_file": "8df324637887759b9ae0543b06cb6efa_76457_1538669332.jpg", "accent": "/ˈbæfl/", "mean_cn": "v.难住；使困惑；阻碍；  n.挡板", "mean_en": "to confuse somebody completely; to be too difficult or strange for somebody to understand or explain", "sentence_phrase": "", "deformation_img": "d_106_282_0_2_20150809063513.png", "sentence": "The math problem really baffled him.", "sentence_trans": "这道数学题真的难住他了。", "sentence_audio": "743efe49a962fb6750f3ecbf225169f4_11487_1538669347.mp3", "cloze_data": "{\"syllable\":\"baf-fle\"", "cloze": "baff[le]", "options": "[\"al|el|nl|ol\"]", "tips": "[[\"baff[le]ment\"]]}", "word_etyma": ""}