{"topic_id": "11093", "word_level_id": "12", "tag_id": "0", "word": "apprehend", "word_audio": "apprehend.mp3", "image_file": "3_0_20170105071032_38464_c.jpg", "accent": "/ˌæprɪˈhend/", "mean_cn": "v.逮捕；把…视作；理解，领会", "mean_en": "(of the police) to catch somebody and arrest them", "sentence_phrase": "apprehended by", "deformation_img": "", "sentence": "The driver was finally apprehended by the police for speeding.", "sentence_trans": "那名驾驶员最终因超速而被警察逮捕。", "sentence_audio": "3_0_20170105071032_77908_c.aac", "cloze_data": "{\"syllable\":\"ap-pre-hend\"", "cloze": "appre-h[en]d", "options": "[\"in|on|un|an|e|i|a|o|u\"]", "tips": "[[\"h[en]dly\"", "word_etyma": "ap一再 ＋ prehend抓住 → 一再抓住人或某个要点 → apprehend理解；忧虑"}