{"topic_id": "6917", "word_level_id": "14", "tag_id": "0", "word": "requisite", "word_audio": "us_requisite_20231212143815031_979d80b042ff87a52830.mp3", "image_file": "requisite_6917_20231106_559553ac.jpg", "accent": "/ˈrekwɪzɪt/", "mean_cn": "n.必需品；  adj.需要的，必不可少的，必备的", "mean_en": "something that you need for a particular purpose", "sentence_phrase": "", "deformation_img": "", "sentence": "The USB cable is a requisite for charging my iPhone.", "sentence_trans": "为了给iPhone充电，我必须有USB数据线。", "sentence_audio": "sa_2_6917_0_3_20150808152541.aac", "cloze_data": "{\"syllable\":\"req-ui-site\"", "cloze": "req-[ui]-site", "options": "[\"uu|ua|ue|uo|iu|u\"]", "tips": "[[\"eq[ui]tes\"", "word_etyma": "re再 + quis寻求，询问 + ite表形容词 → 一再寻求的 → requisite必要的"}