{"topic_id": "3848", "word_level_id": "1157", "tag_id": "0", "word": "approach", "word_audio": "us_approach_20231215135611862_bf576232b7c7b56ce331.mp3", "image_file": "3_0_20170712071115_67363_c.jpg", "accent": "/əˈproʊtʃ/", "mean_cn": "v.接近", "mean_en": "to come near to somebody/something in distance or time", "sentence_phrase": "", "deformation_img": "20141011_00_59_31_945_v3.png", "sentence": "The turtle is slowly approaching the finish line.", "sentence_trans": "乌龟正缓缓爬向终点线。", "sentence_audio": "3cf155ea984b31e4a906549b32ac6af0_11499_1639042259.aac", "cloze_data": "{\"syllable\":\"ap-proach\"", "cloze": "appr[oa]ch", "options": "[\"aa|ae|ai|ao|au|ea|ee|ei|eo|eu|ia|ie|ii|io|iu|oe|oi|oo|ou|ua|ue|ui|uo|uu|ay|ey|ow|oy|ur|al|ir|or|er|ar|a|e|i|o|u\"]", "tips": "[[\"b[oa]st\"", "word_etyma": "ap一再 + proach接近 → approach接近"}