{"topic_id": "5648", "word_level_id": "1157", "tag_id": "0", "word": "severe", "word_audio": "us_severe_20231101105548877_e323fa4782ba050630e0.mp3", "image_file": "062f8469c16f8bb7ac380c077f620397_157876_1644393103.jpg", "accent": "/sɪˈvɪr/", "mean_cn": "adj.严重的", "mean_en": "extremely bad or serious", "sentence_phrase": "", "deformation_img": "7d3312a1da8948573362663f254de762_72643_1539341233.png", "sentence": "He had a severe injury.", "sentence_trans": "他伤势严重。", "sentence_audio": "b117540c2caa579c51d9a25bb3a71b94_9763_1644393061.mp3", "cloze_data": "{\"syllable\":\"se-vere\"", "cloze": "se-v[ere]", "options": "[\"are|ire|ore|ure\"]", "tips": "[[\"rev[ere]\"", "word_etyma": "sever诚恳 + e → severe严肃的，严厉的"}