{"topic_id": "9022", "word_level_id": "15", "tag_id": "0", "word": "excerpt", "word_audio": "us_phoneme_alphabetipa_20240320152250016_f4ab5f7e0808a703e9ca.mp3", "image_file": "3_0_20170105071217_44064_c-gigapixel-scale.jpg", "accent": "/ˈeksɜːrpt/ /ekˈsɜːrpt/", "mean_cn": "n.摘录，节选；  v.摘，选", "mean_en": "\"a short piece of writing", "sentence_phrase": "", "deformation_img": "20140726_02_28_42_7_v3.png", "sentence": "I took an excerpt from this book and \\nused it in my essay. ", "sentence_trans": "我从这本书中摘录了一段话用在我的论文里面。", "sentence_audio": "3_0_20170105071217_87645_c.aac", "cloze_data": "{\"syllable\":\"ex-cerpt\"", "cloze": "ex-c[er]pt", "options": "[\"ar|ir|or|ur|a\"]", "tips": "[[\"unexc[er]pted\"]]}", "word_etyma": "ex向外 + cerpt撕扯 → 撕下来的一段 → excerpt摘录，节选"}