{"topic_id": "19496", "word_level_id": "1157", "tag_id": "0", "word": "football", "word_audio": "football.mp3", "image_file": "i_76_12760_0_4_20150809030914-gigapixel-scale.jpg", "accent": "/ˈfʊtbɔːl/", "mean_cn": "n.\\u003c英\\u003e足球", "mean_en": "\"a game played by two teams of 11 players", "sentence_phrase": "", "deformation_img": "d_93_12760_0_4_20150809002033.png", "sentence": "He loved football from a young age.", "sentence_trans": "他从小就热爱足球。", "sentence_audio": "73358e21d8dede5d_1266763311996644186_250117.mp3", "cloze_data": "{\"syllable\":\"foot-ball\"", "cloze": "foot-b[all]", "options": "[\"ald|alk|alm|alt|ial\"]", "tips": "[[\"b[all]\"", "word_etyma": "foot脚 + ball球 → football足球比赛；足球"}