{"topic_id": "15841", "word_level_id": "12", "tag_id": "0", "word": "alfalfa", "word_audio": "alfalfa.mp3", "image_file": "i_12_15841_0_2_20150808183822.jpg", "accent": "/ælˈfælfə/", "mean_cn": "n.苜蓿", "mean_en": "a type of plant that is grown mostly as food for farm animals", "sentence_phrase": "", "deformation_img": "", "sentence": "Alfalfa is a good crop to feed your cows through the winter.", "sentence_trans": "茴蓿是一种冬天喂牛的好作物。", "sentence_audio": "sa_12_15841_0_2_20150808183822.aac", "cloze_data": "{\"syllable\":\"al-fal-fa\"", "cloze": "al-f[al]-fa", "options": "[\"el|le|nl|ol\"]", "tips": "[[\"f[al]cer\"", "word_etyma": ""}