{"topic_id": "8352", "word_level_id": "1157", "tag_id": "0", "word": "actual", "word_audio": "us_actual_20231103181603557_e9b58ebb417444be6d3c.mp3", "image_file": "i_1_8352_0_25_160406174014-gigapixel-scale.jpg", "accent": "/ˈæktʃuəl/", "mean_cn": "adj.实际的，真实的", "mean_en": "used to emphasize something that is real or exists in fact", "sentence_phrase": "the actual fact", "deformation_img": "d_16_8352_0_4_20150808232844.png", "sentence": "\"I refused the red packet", "sentence_trans": "我拒绝了那个红包，但事实上我想要它。", "sentence_audio": "456a98bc45ce31f5_1266883633628425136_250207.mp3", "cloze_data": "{\"syllable\":\"ac-tu-al\"", "cloze": "ac-tu-[al]", "options": "[\"el|le|nl|ol\"]", "tips": "[[\"[al]\"", "word_etyma": "act行动 + ual形容词后缀 → actual现实的，现行的"}