{"topic_id": "10949", "word_level_id": "1157", "tag_id": "0", "word": "equal", "word_audio": "us_equal_20231212163825468_2d177efb9a0067be92bb.mp3", "image_file": "3d591858a172de90abc727b686476ea9_62995_1649323811.jpg", "accent": "/ˈikwəl/", "mean_cn": "adj.相等的；相同的", "mean_en": "\"having the same rights or being treated the same as other people", "sentence_phrase": "", "deformation_img": "d_24_10949_0_4_20150808230455.png", "sentence": "The area of the blue part is equal to that of the other parts.", "sentence_trans": "蓝色部分的面积与其他部分相等。", "sentence_audio": "5228e7d3a39431bc3740e0485df73682_20108_1649323842.mp3", "cloze_data": "{\"syllable\":\"e-qual\"", "cloze": "e-qu[al]", "options": "[\"el|le|nl|ol\"]", "tips": "[[\"equ[al]ing\"", "word_etyma": "equ相等，平均 + al形容词后缀 → 相等的，平等的"}