{"topic_id": "6236", "word_level_id": "15", "tag_id": "0", "word": "comparable", "word_audio": "us_comparable_20231102115159314_c4a4a3910b162c8ac821.mp3", "image_file": "i_1_6236_0_3_20150808124858-gigapixel-scale.jpg", "accent": "/ˈkɑːmpərəbl/", "mean_cn": "adj.类似的，比得上的，可比较的", "mean_en": "similar to somebody/something else and able to be compared", "sentence_phrase": "", "deformation_img": "d_107_6236_0_2_20150809015344.png", "sentence": "The two dogs are comparable in size and strength.", "sentence_trans": "这两条狗在大小和强壮程度方面都不相上下。", "sentence_audio": "sa_1_6236_0_3_20150808124858.aac", "cloze_data": "{\"syllable\":\"com-pa-ra-ble\"", "cloze": "com-p[a]-ra-[ble]", "options": "[\"e|i|o|u\"", "tips": "[[\"p[a]\"", "word_etyma": "\"compar\\u003dcompare比较，对照 + able形容词后缀，可……的 → (to)比得上的；(with)可比较的"}