{"topic_id": "2915", "word_level_id": "14", "tag_id": "0", "word": "epicure", "word_audio": "1dc7b64da22eb014c9e8336e25029f55_17702_1532942463.mp3", "image_file": "8bb483735b206b81dd1769ce54a84b22_147051_1532942431.jpeg", "accent": "/ˈepɪkjʊr/", "mean_cn": "n.美食家；享乐主义者", "mean_en": "a person who appreciates fine food and drink", "sentence_phrase": "", "deformation_img": "20140909_15_16_10_112_v3.png", "sentence": "The epicure is enjoying the expertly prepared dishes.", "sentence_trans": "美食家在享受这些精心制作的佳肴。", "sentence_audio": "ef5f28933ba7461a50a1290fe6b4ccc2_25776_1553658809.mp3", "cloze_data": "{\"syllable\":\"epi-cure\"", "cloze": "epi-c[ure]", "options": "[\"are|ere|ire|ore\"]", "tips": "[[\"rec[ure]\"", "word_etyma": ""}