{"topic_id": "4009", "word_level_id": "1157", "tag_id": "0", "word": "ideology", "word_audio": "wa_106_4009_0_2_20150809065157.aac", "image_file": "ab5f8350f4afdb85a38d0fa6565df930_200799_1564730339.jpg", "accent": "/ˌaɪdiˈɑːlədʒi/", "mean_cn": "n.意识形态，思想（体系）", "mean_en": "\"a set of ideas that an economic or political system is based on; a set of beliefs", "sentence_phrase": "", "deformation_img": "9e307656c7c8f93772b2ad5c915563d8_63687_1551258893.png", "sentence": "The animals formed two opposite ideologies based on what they eat.", "sentence_trans": "动物根据它们吃的东西形成了两种相反的意识形态。", "sentence_audio": "827ed9076d5602bba3596af29ac2eb6e_42148_1564730328.mp3", "cloze_data": "{\"syllable\":\"ide-o-lo-gy\"", "cloze": "ide-[o]-l[o]-gy", "options": "[\"a|e|i|u\"", "tips": "[[\"[o]da\"", "word_etyma": "ideo思想 + logy名词后缀：体系 → ideology思想体系，意识形态"}