{"topic_id": "3760", "word_level_id": "15", "tag_id": "0", "word": "transmute", "word_audio": "transmute.mp3", "image_file": "31b90a4913bb88f4e2f1775a234dae30_83624_1701932830.jpeg", "accent": "/trænzˈmjuːt/", "mean_cn": "v.使改变，使变形", "mean_en": "\"to change", "sentence_phrase": "transmuted her skin", "deformation_img": "20140825_16_44_06_510_v3.png", "sentence": "\"The treatment transmuted her skin", "sentence_trans": "治疗改变了她的皮肤，给了她一张更年轻的脸。", "sentence_audio": "sa_4_3760_0_3_20150808145645.aac", "cloze_data": "{\"syllable\":\"trans-mute\"", "cloze": "tr[an]s-mute", "options": "[\"en|in|on|un|e|i|a|o|u\"]", "tips": "[[\"tr[an]sbay\"", "word_etyma": "trans横进去 + mute变 → 变过去 → 变形"}